turbo_markdown/__init__.py
turbo_markdown/cli.py
turbo_markdown/template.py
turbo_markdown/turbo_markdown.py
turbo_markdown/util.py
turbo_markdown/static/css/github.css
turbo_markdown/static/img/folder-fill.png
turbo_markdown/static/img/folder-open-fill.png
turbo_markdown/static/img/folder.png
turbo_markdown/static/js/jquery-3.2.1.min.js
turbo_markdown-0.5.0.dist-info/DESCRIPTION.rst
turbo_markdown-0.5.0.dist-info/METADATA
turbo_markdown-0.5.0.dist-info/RECORD
turbo_markdown-0.5.0.dist-info/WHEEL
turbo_markdown-0.5.0.dist-info/entry_points.txt
turbo_markdown-0.5.0.dist-info/metadata.json
turbo_markdown-0.5.0.dist-info/top_level.txt
