Metadata-Version: 2.0
Name: turbo-markdown
Version: 0.5.0
Summary: A cli tool to view local markdown files
Home-page: https://github.com/wecatch/turbo_markdown
Author: wecatch
Author-email: zhyq0826@126.com
License: MIT license
Keywords: markdown,turbo
Platform: UNKNOWN
Classifier: Development Status :: 2 - Pre-Alpha
Classifier: Intended Audience :: Developers
Classifier: License :: OSI Approved :: MIT License
Classifier: Natural Language :: English
Classifier: Programming Language :: Python :: 2
Classifier: Programming Language :: Python :: 2.6
Classifier: Programming Language :: Python :: 2.7
Requires-Dist: Click (>=6.0)
Requires-Dist: mistune
Requires-Dist: turbo (>=0.4.5)
